pyshipstation/__init__.py
pyshipstation/common/__init__.py
pyshipstation/common/base_model.py
pyshipstation/v1/__init__.py
pyshipstation/v1/models/__init__.py
pyshipstation/v1/models/address.py
pyshipstation/v1/models/advanced_options.py
pyshipstation/v1/models/order.py
pyshipstation/v1/models/order_item.py
pyshipstation/v1/sync/__init__.py
pyshipstation/v1/sync/client.py
pyshipstation/v2/__init__.py
pyshipstation/v2/models/__init__.py
pyshipstation/v2/models/inventory_response.py
pyshipstation/v2/sync/__init__.py
pyshipstation/v2/sync/client.py
pyshipstation-0.0.10.dist-info/METADATA
pyshipstation-0.0.10.dist-info/WHEEL
pyshipstation-0.0.10.dist-info/top_level.txt
pyshipstation-0.0.10.dist-info/RECORD
