Metadata-Version: 2.4
Name: pyshipstation
Version: 0.0.10
Project-URL: Homepage, https://github.com/go-swag/py-shipstation
Project-URL: Issues, https://github.com/go-swag/py-shipstation/issues
Classifier: Programming Language :: Python :: 3
Classifier: Operating System :: OS Independent
Requires-Python: >=3.12
Requires-Dist: requests>=2.32.3
Requires-Dist: pydantic>=2.10.6
